{"duid":"DALNTH01","station_name":"nan","region":"nan","fuel_category":"Battery","capacity_mw":30.0,"technology":"nan","connection_point":"SDAN1D","market":"NEM","lgc_eligible":false,"mlf":{"years":["FY17-18","FY18-19","FY19-20","FY20-21","FY21-22","FY22-23","FY23-24","FY24-25"],"values":[0.8848,0.888,0.9045,0.9193,0.9212,0.9432,0.8954,0.9092]},"constraints":{"top_constraints":[{"id":"S>NIL_HUWT_STBG3","description":"Out = Nil; Limit Snowtown WF generation to avoid Snowtown - Bungama line OL on loss of Hummocks - Waterloo line.[Note: Constraint Swamped when Wattle PT when generating >=60 MW)","total_hours":491.9},{"id":"S>>NIL_RBTX_RBTX_1","description":"Out= Nil, avoid O/L of one Robertstown 275/132kV TX on trip of other Robertstown 275/132kV TX, Feedback","total_hours":283.6},{"id":"S>NIL_BWMP_HUWT","description":"Out= Nil, avoid O/L Hummocks - Waterloo 132kV on trip of Blyth West- Munno Para 275kV line, Feedback","total_hours":157.6},{"id":"S>S_WERB_TWPA_TPRS","description":"Out= Robertstown - MWP4 - Waterloo East O/S(offloads MWP4 SF), avoid O/L Templers-Roseworthy 132kV line on trip of Templers West-Para 275kV line, Feedback","total_hours":116.6},{"id":"S>>NIL_TWPA_TPRS","description":"Out= NIL, avoid O/L Templers-Roseworthy 132kV line on trip of Templers West-Para 275kV line, Feedback","total_hours":91.4},{"id":"S>>BGBW_TWPA_TPRS","description":"Out= Bungama - Blyth West 275kV line, avoid O/L Templers-Roseworthy 132kV line on trip of Templers West- Para 275kV line, Feedback","total_hours":55.7},{"id":"S>>NIL_RBTU_RBTU","description":"Out= NIL, avoid O/L Robertstown-Tungkillo 275kV line 1 or 2 on trip of parallel Robertstown-Tungkillo 275kV line 2 or 1, Feedback","total_hours":44.1},{"id":"S>NIL_BWMP_RHBR-T","description":"Out= Nil, avoid O/L Redhill-Brinkworth  T 132kV line on trip of Blyth West-Munno Para 275kV line, Feedback","total_hours":43.0},{"id":"S>>NIL_BWMP_RBTU","description":"Out= NIL, avoid O/L Robertstown-Tungkillo 275kV line 1 or 2 on trip of Blyth West-Munno Para 275kV line, Feedback","total_hours":35.6},{"id":"S>RBMW4_TWPA_TPRS","description":"Out= Robertstown - MWP4 O/S, avoid O/L Templers-Roseworthy 132kV line on trip of Templers West-Para 275kV line, Feedback","total_hours":33.9},{"id":"S>NIL_HUWT_STBG","description":"Out = Nil; avoid O/L on Snowtown - Bungama line 132kV on loss of Hummocks - Waterloo 132kV line, Feedback","total_hours":27.8},{"id":"S>>BDBU_RBTU_RBTU","description":"Out= Bundey to Buronga 330kV, avoid O/L Robertstown-Tungkillo 275kV line 1 or 2 on trip of parallel Robertstown-Tungkillo 275kV line 2 or 1, Feedback","total_hours":26.5},{"id":"S>>NIL_BWMP_WTTP","description":"Out= Nil, avoid O/L Waterloo - Templers 132kV on trip of Blyth West- Munno Para 275kV line, Feedback","total_hours":24.3},{"id":"S>>DVBG_RBTU_RBTU","description":"Out= Davenport-Bungama 275kV line, avoid O/L Robertstown to Tungkillo 275kV line 1 or 2 on trip of the other Robertstown to Tungkillo 275kV line, Feedback","total_hours":16.2},{"id":"S>X-MNWT+CB_01","description":"Out= Mintaro-Waterloo 132kV line + associated line CBs O/S, avoid O/L Snowtown-Bungama T 132kV line on trip of Waterloo -Templers 132kV line (this offloads Hummocks-Waterloo 132 kV line), Feedback","total_hours":16.2}],"heatmap":{"months":["2024-04","2024-05","2024-06","2024-07","2024-08","2024-09","2024-10","2024-11","2024-12","2025-01","2025-02","2025-03","2025-04","2025-05","2025-06","2025-07","2025-08","2025-09","2025-10","2025-11","2025-12","2026-01","2026-02","2026-03"],"constraints":{"S>NIL_HUWT_STBG3":[24.2,18.6,12.0,13.7,30.4,7.2,8.2,23.1,23.5,31.5,28.3,17.8,8.8,11.8,28.9,16.9,30.0,9.4,8.4,14.1,31.2,68.8,25.1,0],"S>>NIL_RBTX_RBTX_1":[0,0,1.6,0.8,18.8,8.7,6.2,7.6,14.0,10.0,6.2,0.8,6.7,6.0,67.7,46.7,4.6,3.2,9.9,21.1,5.4,5.4,27.4,4.8],"S>NIL_BWMP_HUWT":[0,0,0.7,1.0,110.4,31.3,0,0,0.3,2.2,0,2.8,0.7,0.9,0.4,0,0,1.9,1.1,0,0.9,2.8,0.2,0],"S>S_WERB_TWPA_TPRS":[0,0,0,0,8.4,0.8,0,0,0,0,0,0,0,2.1,82.6,19.9,0,2.8,0,0,0,0,0,0],"S>>NIL_TWPA_TPRS":[2.9,1.4,19.8,11.2,16.7,2.8,1.3,0.6,1.8,1.7,0.7,1.0,0.6,0.2,3.1,3.4,0.1,7.2,0.8,1.5,0.9,1.6,7.3,2.8],"S>>BGBW_TWPA_TPRS":[3.0,0,0,0,0,0,0,0,0,0,0,0,0,22.4,0,0,30.3,0,0,0,0,0,0,0],"S>>NIL_RBTU_RBTU":[0,0,0,0.1,0.8,0.7,0.1,0.1,0,0.1,0.7,2.9,0,0.5,1.8,20.2,2.1,7.6,2.2,4.2,0,0,0,0],"S>NIL_BWMP_RHBR-T":[0,0,0,0.1,1.6,2.1,0.4,0,0,0,0,1.1,0.2,0.1,3.8,3.1,1.0,4.3,2.9,4.0,2.8,12.3,2.4,0.8],"S>>NIL_BWMP_RBTU":[0,0,0,0,0,0,0,0,0,0,0,0,0,0.3,35.3,0,0,0,0,0,0,0,0,0],"S>RBMW4_TWPA_TPRS":[0,0,0,0,0,0,0,0,0,0,0,0,0,0,0,20.8,0,0,0,0,0,0,13.1,0],"S>NIL_HUWT_STBG":[0,0,0,0,0,0,0,0,0,0,0,0,0,0,0,0,0,0,0,0,0,0,12.2,15.6],"S>>BDBU_RBTU_RBTU":[0,0,0,0,0,0,0.8,3.2,8.1,4.0,1.2,0,0,0,0,9.2,0,0,0,0,0,0,0,0],"S>>NIL_BWMP_WTTP":[0.2,0.4,0,1.2,5.7,0,0,0,0,0,0.2,0.1,0,0,6.3,7.0,1.8,0,0,0,0,0,1.4,0],"S>>DVBG_RBTU_RBTU":[0,0,0,0,0,0,0,0,0,0,0,1.5,0,5.0,0,0,8.8,0,0,0.9,0,0,0,0],"S>X-MNWT+CB_01":[0,0,0,0,0,0,0,0,0,0,0,16.2,0,0,0,0,0,0,0,0,0,0,0,0]}}}}