{"duid":"LBB1","station_name":"Lake Bonney BESS1","region":"SA1","fuel_category":"Battery","capacity_mw":25.0,"technology":"Storage","connection_point":"","monthly":{"months":["2026-01","2026-02"],"generation_mwh":[919.0,842.0],"revenue_aud":[482165.0,84370.0],"capacity_factor":[0.0494,0.0501],"curtailment_pct":[NaN,NaN],"captured_price":[524.81,100.23],"avg_rrp":[152.25,56.0],"price_capture_ratio":[3.447,1.7898]},"price_distribution":{"bins":["<0","0-50","50-100","100-200","200-300","300+"],"generation_share":[0.1719,0.1756,0.2321,0.2677,0.0754,0.0774]}}