{"duid":"LIMOSF11","station_name":"Limondale Solar Farm 1","region":"NSW1","fuel_category":"Solar","capacity_mw":275.0,"technology":"Renewable","connection_point":"","monthly":{"months":["2026-01","2026-02"],"generation_mwh":[38981.0,40978.0],"revenue_aud":[1321409.0,2424131.0],"capacity_factor":[0.1905,0.2217],"curtailment_pct":[0.1582,0.097],"captured_price":[39.75,69.36],"avg_rrp":[67.22,83.76],"price_capture_ratio":[0.5913,0.8281]},"mlf":{"years":["FY19-20","FY20-21","FY21-22","FY22-23","FY23-24","FY24-25","FY25-26"],"values":[0.7628,0.7907,0.807,0.8314,0.8255,0.7774,0.8529]},"price_distribution":{"bins":["<0","0-50","50-100","100-200","200-300","300+"],"generation_share":[0.0966,0.4909,0.3378,0.0635,0.0078,0.0032]}}