{"duid":"MLWF1","station_name":"Mortons Lane Wind Farm","region":"VIC1","fuel_category":"Wind","capacity_mw":20.0,"technology":"Renewable","connection_point":"","monthly":{"months":["2026-01","2026-02"],"generation_mwh":[4964.0,3431.0],"revenue_aud":[129739.0,123094.0],"capacity_factor":[0.3336,0.2553],"curtailment_pct":[NaN,NaN],"captured_price":[26.09,35.81],"avg_rrp":[38.58,44.7],"price_capture_ratio":[0.6762,0.8013]},"mlf":{"years":["FY15-16","FY16-17","FY17-18","FY18-19","FY19-20","FY20-21","FY21-22","FY22-23","FY23-24","FY24-25","FY25-26"],"values":[1.03,1.0339,1.0322,1.0149,1.0019,1.0063,1.0035,0.9972,0.9933,0.9993,1.0018]},"price_distribution":{"bins":["<0","0-50","50-100","100-200","200-300","300+"],"generation_share":[0.3591,0.3095,0.2645,0.056,0.0046,0.0063]}}