{"duid":"VPGS3","station_name":"Valley Power Peaking Facility","region":"VIC1","fuel_category":"Fossil","capacity_mw":50.0,"technology":"Combustion","connection_point":"","monthly":{"months":["2026-01","2026-02"],"generation_mwh":[250.0,23.0],"revenue_aud":[124818.0,416.0],"capacity_factor":[0.0067,0.0007],"curtailment_pct":[NaN,NaN],"captured_price":[508.23,18.1],"avg_rrp":[38.55,45.06],"price_capture_ratio":[13.1829,0.4018]},"mlf":{"years":["FY15-16","FY16-17","FY17-18","FY18-19","FY19-20","FY20-21","FY21-22","FY22-23","FY23-24","FY24-25","FY25-26"],"values":[0.9742,0.9723,0.9801,0.9798,0.9754,0.976,0.9759,0.9783,0.9782,0.9809,0.9815]},"price_distribution":{"bins":["<0","0-50","50-100","100-200","200-300","300+"],"generation_share":[0.0,0.5,0.0043,0.1124,0.0478,0.3355]}}